pyhackasm/__init__.py
pyhackasm/__main__.py
pyhackasm/assembler.py
pyhackasm/cli.py
pyhackasm-0.1.1.dist-info/entry_points.txt
pyhackasm-0.1.1.dist-info/LICENSE
pyhackasm-0.1.1.dist-info/WHEEL
pyhackasm-0.1.1.dist-info/METADATA
pyhackasm-0.1.1.dist-info/RECORD
